Metadata-Version: 2.1
Name: Python-video-annotator-module-path-editor
Version: 0.5.28
Summary: UNKNOWN
Home-page: https://bitbucket.org/fchampalimaud/pythonvideoannotator-module-patheditor
Author: ['Ricardo Ribeiro']
Author-email: ricardojvr@gmail.com
License: UNKNOWN
Platform: UNKNOWN
